dirty_models_sphinx/__init__.py
dirty_models_sphinx/documenters.py
dirty_models_sphinx-0.6.2.dist-info/LICENSE
dirty_models_sphinx-0.6.2.dist-info/METADATA
dirty_models_sphinx-0.6.2.dist-info/WHEEL
dirty_models_sphinx-0.6.2.dist-info/top_level.txt
dirty_models_sphinx-0.6.2.dist-info/zip-safe
dirty_models_sphinx-0.6.2.dist-info/RECORD
