Metadata-Version: 2.1
Name: dirty-models-sphinx
Version: 0.6.2
Summary: Sphinx extension for dirty models
Home-page: https://github.com/alfred82santa/dirty-models-sphinx
Author: alfred82santa
Author-email: alfred82santa@gmail.com
License: GPLv2
Platform: UNKNOWN
Classifier: Intended Audience :: Developers
Classifier: Programming Language :: Python
Classifier: Programming Language :: Python :: 3.3
Classifier: Programming Language :: Python :: 3.4
Classifier: Programming Language :: Python :: 3.5
Classifier: Programming Language :: Python :: 3.6
Classifier: Programming Language :: Python :: 3.7
Classifier: Programming Language :: Python :: 3.8
Classifier: Programming Language :: Python :: 3.9
Classifier: Programming Language :: Python :: 3.10
Classifier: License :: OSI Approved :: GNU General Public License v2 (GPLv2)
Classifier: Development Status :: 4 - Beta
License-File: LICENSE
Requires-Dist: dirty-models
Requires-Dist: sphinx
